edr_pydantic/__init__.py
edr_pydantic/base_model.py
edr_pydantic/capabilities.py
edr_pydantic/collections.py
edr_pydantic/data_queries.py
edr_pydantic/extent.py
edr_pydantic/link.py
edr_pydantic/observed_property.py
edr_pydantic/parameter.py
edr_pydantic/py.typed
edr_pydantic/unit.py
edr_pydantic/variables.py
edr_pydantic-0.7.0.dist-info/licenses/LICENSE
edr_pydantic-0.7.0.dist-info/WHEEL
edr_pydantic-0.7.0.dist-info/METADATA
edr_pydantic-0.7.0.dist-info/RECORD
