Metadata-Version: 2.4
Name: edr-pydantic
Version: 0.7.0
Summary: Pydantic models for OGC Environmental Data (EDR) API
Keywords: EDR,Pydantic
Author-email: KNMI Data Platform Team <opendata@knmi.nl>
Requires-Python: >=3.8
Classifier: Intended Audience :: Information Technology
Classifier: Intended Audience :: Science/Research
Classifier: License :: OSI Approved :: Apache Software License
Classifier: Programming Language :: Python :: 3.8
Classifier: Programming Language :: Python :: 3.9
Classifier: Programming Language :: Python :: 3.10
Classifier: Programming Language :: Python :: 3.11
Classifier: Programming Language :: Python :: 3.12
Classifier: Programming Language :: Python :: 3.13
Classifier: Topic :: Scientific/Engineering :: GIS
Classifier: Typing :: Typed
License-File: LICENSE
Requires-Dist: pydantic>=2.3,<3
Requires-Dist: typing-extensions>=4.12.2
Requires-Dist: pre-commit ; extra == "dev"
Requires-Dist: pytest ; extra == "test"
Requires-Dist: pytest-cov ; extra == "test"
Project-URL: Source, https://github.com/knmi/edr-pydantic
Provides-Extra: dev
Provides-Extra: test
